lampo_py/__init__.py
lampo_py/lampo.py
lampo_py-0.0.1a7.dist-info/METADATA
lampo_py-0.0.1a7.dist-info/WHEEL
lampo_py-0.0.1a7.dist-info/RECORD
