Metadata-Version: 2.1
Name: lampo-py
Version: 0.0.1a7
Summary: 
Author: Vincenzo Palazzo
Author-email: vincenzopalazzodev@gmail.com
Requires-Python: >=3.7
Classifier: Programming Language :: Python :: 3
Classifier: Programming Language :: Python :: 3.7
Classifier: Programming Language :: Python :: 3.8
Classifier: Programming Language :: Python :: 3.9
Classifier: Programming Language :: Python :: 3.10
Classifier: Programming Language :: Python :: 3.11
Requires-Dist: cffi (>=1.15.1,<2.0.0)
